{
  "parent": "minecraft:recipes/root",
  "criteria": {
    "has_pale_oak_pipe": {
      "conditions": {
        "items": [
          {
            "items": "ironpipes:pale_oak_pipe"
          }
        ]
      },
      "trigger": "minecraft:inventory_changed"
    },
    "has_the_recipe": {
      "conditions": {
        "recipe": "ironpipes:pale_oak_fitting"
      },
      "trigger": "minecraft:recipe_unlocked"
    }
  },
  "requirements": [
    [
      "has_the_recipe",
      "has_pale_oak_pipe"
    ]
  ],
  "rewards": {
    "recipes": [
      "ironpipes:pale_oak_fitting"
    ]
  }
}